expsuite.py
expsuite-0.1.1.dist-info/LICENSE
expsuite-0.1.1.dist-info/METADATA
expsuite-0.1.1.dist-info/WHEEL
expsuite-0.1.1.dist-info/top_level.txt
expsuite-0.1.1.dist-info/RECORD
