Metadata-Version: 2.1
Name: expsuite
Version: 0.1.1
Summary: PyExperimentSuite is an open source software tool written in Python, that supports scientists, engineers and others to conduct automated software experiments on a larger scale with numerous different parameters
Home-page: UNKNOWN
Author: Thomas Rueckstiess
License: UNKNOWN
Platform: UNKNOWN
Classifier: Programming Language :: Python :: 3
Classifier: License :: OSI Approved :: BSD License
Classifier: Operating System :: OS Independent
Requires-Python: >=3.6
License-File: LICENSE
Requires-Dist: numpy
